ustcnlpkit
