Metadata-Version: 1.0
Name: ustcnlpkit
Version: 1.0.1
Summary: test version
Home-page: UNKNOWN
Author: linhaowen
Author-email: linhaowen04212@163.com
License: UNKNOWN
Platform: UNKNOWN
